ersilia_pack_utils/__init__.py
ersilia_pack_utils/core.py
ersilia_pack_utils-0.1.5.dist-info/licenses/LICENSE
ersilia_pack_utils-0.1.5.dist-info/METADATA
ersilia_pack_utils-0.1.5.dist-info/WHEEL
ersilia_pack_utils-0.1.5.dist-info/top_level.txt
ersilia_pack_utils-0.1.5.dist-info/RECORD
