Metadata-Version: 2.4
Name: ersilia-pack-utils
Version: 0.1.5
Summary: utils for ersilia pack
Author-email: Your Name <you@ersilia.io>
License:                     GNU GENERAL PUBLIC LICENSE
Requires-Python: >=3.8
License-File: LICENSE
Requires-Dist: numpy>=1.21
Provides-Extra: dev
Requires-Dist: pytest; extra == "dev"
Requires-Dist: black; extra == "dev"
Requires-Dist: flake8; extra == "dev"
Dynamic: license-file
